begin/__init__.py
begin/cmdline.py
begin/completion.py
begin/context.py
begin/convert.py
begin/extensions.py
begin/formatters.py
begin/main.py
begin/subcommands.py
begin/utils.py
begin/version.py
begin/wrappable.py
begins-0.8.dist-info/DESCRIPTION.rst
begins-0.8.dist-info/METADATA
begins-0.8.dist-info/pydist.json
begins-0.8.dist-info/RECORD
begins-0.8.dist-info/top_level.txt
begins-0.8.dist-info/WHEEL
